treemenu
