Metadata-Version: 1.1
Name: django-treemenu
Version: 0.1.1
Summary: Another reusable app for organize tree menus on django site
Home-page: https://github.com/artofhuman/django-treemenu
Author: Pupkov Semen
Author-email: semen.pupvko@gmail.com
License: UNKNOWN
Platform: UNKNOWN
Classifier: Environment :: Web Environment
Classifier: Framework :: Django
Classifier: Intended Audience :: Developers
Classifier: Operating System :: OS Independent
Classifier: Programming Language :: Python
Classifier: Framework :: Django
